lakey_finicity/__init__.py
lakey_finicity/api_http_client.py
lakey_finicity/finicity_client.py
lakey_finicity/utils.py
lakey_finicity/models/__init__.py
lakey_finicity/models/birth_date.py
lakey_finicity/models/content_type.py
lakey_finicity/models/sort_order.py
lakey_finicity/models/account/__init__.py
lakey_finicity/models/account/account.py
lakey_finicity/models/account/account_ach_details.py
lakey_finicity/models/account/account_detail.py
lakey_finicity/models/account/account_owner.py
lakey_finicity/models/account/account_type.py
lakey_finicity/models/account/aggregation_status_code.py
lakey_finicity/models/account/credit_line_account_detail.py
lakey_finicity/models/account/deposit_account_detail.py
lakey_finicity/models/account/investment_account_detail.py
lakey_finicity/models/account/loan_account_detail.py
lakey_finicity/models/connect/__init__.py
lakey_finicity/models/connect/answered_mfa_question.py
lakey_finicity/models/connect/connect_type.py
lakey_finicity/models/connect/mfa_question.py
lakey_finicity/models/consumer/__init__.py
lakey_finicity/models/consumer/consumer.py
lakey_finicity/models/customer/__init__.py
lakey_finicity/models/customer/customer.py
lakey_finicity/models/institution/__init__.py
lakey_finicity/models/institution/institution.py
lakey_finicity/models/institution/institution_account_type.py
lakey_finicity/models/institution/institution_address.py
lakey_finicity/models/institution/login_field.py
lakey_finicity/models/report/__init__.py
lakey_finicity/models/report/cadence.py
lakey_finicity/models/report/income_stream_transaction_record.py
lakey_finicity/models/report/permissible_purpose.py
lakey_finicity/models/report/report_constraints.py
lakey_finicity/models/report/report_custom_field.py
lakey_finicity/models/report/report_status.py
lakey_finicity/models/report/report_summary.py
lakey_finicity/models/report/report_type.py
lakey_finicity/models/report/transaction_record.py
lakey_finicity/models/report/voa/__init__.py
lakey_finicity-0.0.1.dist-info/LICENSE
lakey_finicity-0.0.1.dist-info/METADATA
lakey_finicity-0.0.1.dist-info/WHEEL
lakey_finicity-0.0.1.dist-info/top_level.txt
lakey_finicity-0.0.1.dist-info/RECORD
