Metadata-Version: 2.1
Name: lakey-finicity
Version: 0.0.1
Summary: A client library for Finicity's API
Home-page: https://github.com/jeremydeanlakey/lakey-finicity-python
Author: Jeremy Dean Lakey
Author-email: jeremy.lakey@gmail.com
License: UNKNOWN
Platform: UNKNOWN
Classifier: Programming Language :: Python :: 3
Classifier: License :: OSI Approved :: MIT License
Classifier: Operating System :: OS Independent
Requires-Python: >=3.7
